test_culture_client/__init__.py
test_culture_client/client.py
test_culture_client/endpoints/__init__.py
test_culture_client/endpoints/folder.py
test_culture_client/endpoints/test_case.py
test_culture_client/endpoints/test_cycle.py
test_culture_client/endpoints/test_run.py
test_culture_client/endpoints/unit.py
test_culture_client/models/__init__.py
test_culture_client/models/common.py
test_culture_client/models/folder.py
test_culture_client/models/link.py
test_culture_client/models/space.py
test_culture_client/models/suit.py
test_culture_client/models/test_case/__init__.py
test_culture_client/models/test_case/data.py
test_culture_client/models/test_case/entry.py
test_culture_client/models/test_case/formatted.py
test_culture_client/models/test_case/parameter.py
test_culture_client/models/test_cycle.py
test_culture_client/models/test_run.py
test_culture_client/models/tql.py
test_culture_client/models/unit.py
test_culture_client/utils.py
test_culture_client-1.3.0.dist-info/METADATA
test_culture_client-1.3.0.dist-info/WHEEL
test_culture_client-1.3.0.dist-info/RECORD
