Metadata-Version: 2.3
Name: test-culture-client
Version: 1.3.0
Summary: API Client for Platform V Works::TestCulture
License: MIT
Author: Lokkina Olesia
Requires-Python: <4.0,>=3.10
Classifier: License :: OSI Approved :: MIT License
Classifier: Programming Language :: Python :: 3
Classifier: Programming Language :: Python :: 3.10
Classifier: Programming Language :: Python :: 3.11
Classifier: Programming Language :: Python :: 3.12
Classifier: Programming Language :: Python :: 3.13
Requires-Dist: pydantic (>=2.11.4,<3.0.0)
Requires-Dist: requests (>=2.32.3,<3.0.0)
